.editorconfig
LICENSE.txt
MANIFEST.in
README.rst
setup.py
django_akamai/__init__.py
django_akamai/purge.py
django_akamai/signals.py
django_akamai/tasks.py
django_akamai.egg-info/PKG-INFO
django_akamai.egg-info/SOURCES.txt
django_akamai.egg-info/dependency_links.txt
django_akamai.egg-info/requires.txt
django_akamai.egg-info/top_level.txt