Metadata-Version: 1.0
Name: django-akamai
Version: 2.0.0
Summary: A Django app for performing Akamai purge requests
Home-page: https://github.com/beathan/django-akamai
Author: Ben Boyd
Author-email: beathan@gmail.com
License: UNKNOWN
Platform: UNKNOWN
